websockethost/__init__.py
websockethost/basicCGIserver.py
websockethost/basicserverhttp.py
websockethost/socketServerClient/SqlSys.py
websockethost/socketServerClient/__init__.py
websockethost/socketServerClient/client.py
websockethost/socketServerClient/server.py
websockethost/socketServerClient/ThreadScripts/ThreadForClient.py
websockethost/socketServerClient/ThreadScripts/__init__.py
websockethost-0.1.11.dist-info/METADATA
websockethost-0.1.11.dist-info/WHEEL
websockethost-0.1.11.dist-info/top_level.txt
websockethost-0.1.11.dist-info/RECORD
