Metadata-Version: 2.1
Name: websockethost
Version: 0.1.11
Summary: Web and python socket host (UPD)
Home-page: https://github.com/lamalice20/websockethost
Author: lamalice20
Author-email: discord974a@gmail.com
Requires-Python: >=3.12.5
